mlstdb/__about__.py
mlstdb/__init__.py
mlstdb/__main__.py
mlstdb/utils.py
mlstdb/cli/__init__.py
mlstdb/cli/fetch.py
mlstdb/cli/update.py
mlstdb/core/__init__.py
mlstdb/core/auth.py
mlstdb/core/config.py
mlstdb/core/download.py
mlstdb/data/__init__.py
mlstdb/data/mlst_schemes_all.tab
mlstdb/data/scheme_uris.tab
mlstdb-0.2.0.dist-info/METADATA
mlstdb-0.2.0.dist-info/WHEEL
mlstdb-0.2.0.dist-info/entry_points.txt
mlstdb-0.2.0.dist-info/licenses/LICENSE.txt
mlstdb-0.2.0.dist-info/RECORD
