Metadata-Version: 2.4
Name: mlstdb
Version: 0.2.0
Summary: A Python package to update and manage the MLST database for the MLST tool.
Project-URL: Documentation, https://github.com/himal2007/mlstdb#readme
Project-URL: Issues, https://github.com/himal2007/mlstdb/issues
Project-URL: Source, https://github.com/himal2007/mlstdb
Author-email: Himal Shrestha <stha.himal2007@gmail.com>
License-Expression: GPL-3.0-or-later
License-File: LICENSE.txt
Classifier: Development Status :: 4 - Beta
Classifier: Programming Language :: Python :: 3
Classifier: Programming Language :: Python :: 3.8
Classifier: Programming Language :: Python :: 3.9
Classifier: Programming Language :: Python :: 3.10
Classifier: Programming Language :: Python :: 3.11
Classifier: Programming Language :: Python :: 3.12
Classifier: Programming Language :: Python :: Implementation :: CPython
Classifier: Programming Language :: Python :: Implementation :: PyPy
Requires-Python: >=3
Requires-Dist: click>=8.0.0
Requires-Dist: configparser>=5.0.0
Requires-Dist: rauth>=0.7.3
Requires-Dist: requests>=2.25.0
Requires-Dist: tqdm>=4.65.0
Provides-Extra: dev
Requires-Dist: black>=22.0.0; extra == 'dev'
Requires-Dist: isort>=5.0.0; extra == 'dev'
Requires-Dist: mypy>=1.0.0; extra == 'dev'
Provides-Extra: test
Requires-Dist: pytest-cov>=4.1.0; extra == 'test'
Requires-Dist: pytest>=6.0; extra == 'test'
